tox_wheel/__init__.py
tox_wheel/plugin.py
tox_wheel-1.0.0.dist-info/AUTHORS.rst
tox_wheel-1.0.0.dist-info/LICENSE
tox_wheel-1.0.0.dist-info/METADATA
tox_wheel-1.0.0.dist-info/WHEEL
tox_wheel-1.0.0.dist-info/entry_points.txt
tox_wheel-1.0.0.dist-info/top_level.txt
tox_wheel-1.0.0.dist-info/RECORD
