Metadata-Version: 2.1
Name: tox-wheel
Version: 1.0.0
Summary: A Tox plugin that builds and installs wheels instead of sdist.
Home-page: https://github.com/ionelmc/tox-wheel
Author: Ionel Cristian Mărieș
Author-email: contact@ionelmc.ro
License: BSD-2-Clause
Project-URL: Changelog, https://github.com/ionelmc/tox-wheel/blob/master/CHANGELOG.rst
Project-URL: Issue Tracker, https://github.com/ionelmc/tox-wheel/issues
Keywords: tox,tox-wheel,wheel,pep517,pep518
Platform: UNKNOWN
Classifier: Development Status :: 5 - Production/Stable
Classifier: Intended Audience :: Developers
Classifier: License :: OSI Approved :: BSD License
Classifier: Operating System :: Unix
Classifier: Operating System :: POSIX
Classifier: Operating System :: Microsoft :: Windows
Classifier: Programming Language :: Python
Classifier: Programming Language :: Python :: 3
Classifier: Programming Language :: Python :: 3 :: Only
Classifier: Programming Language :: Python :: 3.6
Classifier: Programming Language :: Python :: 3.7
Classifier: Programming Language :: Python :: 3.8
Classifier: Programming Language :: Python :: 3.9
Classifier: Programming Language :: Python :: 3.10
Classifier: Programming Language :: Python :: Implementation :: CPython
Classifier: Programming Language :: Python :: Implementation :: PyPy
Classifier: Topic :: Utilities
Requires-Python: >=3.6
License-File: LICENSE
License-File: AUTHORS.rst
Requires-Dist: tox (>=3.9.0)
Requires-Dist: wheel (>=0.33.1)
